embedid/__init__.py
embedid/cli.py
embedid/core.py
embedid/manifest.py
embedid-0.1.0.dist-info/METADATA
embedid-0.1.0.dist-info/WHEEL
embedid-0.1.0.dist-info/entry_points.txt
embedid-0.1.0.dist-info/top_level.txt
embedid-0.1.0.dist-info/RECORD
