Metadata-Version: 2.4
Name: embedid
Version: 0.1.0
Summary: Modular watermark protocol for authorship and remix lineage
Author: James The Giblet
License-Expression: MIT
Project-URL: Homepage, https://github.com/james-the-giblet/embedid
Project-URL: Documentation, https://github.com/james-the-giblet/embedid#readme
Keywords: watermark,authorship,remix,sovereignty,protocol
Classifier: Programming Language :: Python :: 3
Classifier: Operating System :: OS Independent
Classifier: Development Status :: 4 - Beta
Classifier: Intended Audience :: Developers
Classifier: Topic :: Software Development :: Version Control
Requires-Python: >=3.7
Dynamic: requires-python
